triopg/__init__.py
triopg/_triopg.py
triopg/_version.py
triopg/exceptions.py
triopg/_tests/__init__.py
triopg/_tests/conftest.py
triopg/_tests/test_triopg.py
triopg-0.6.0.dist-info/LICENSE
triopg-0.6.0.dist-info/LICENSE.APACHE2
triopg-0.6.0.dist-info/LICENSE.MIT
triopg-0.6.0.dist-info/METADATA
triopg-0.6.0.dist-info/WHEEL
triopg-0.6.0.dist-info/top_level.txt
triopg-0.6.0.dist-info/RECORD
