Metadata-Version: 2.1
Name: triopg
Version: 0.6.0
Summary: PostgreSQL client for Trio based on asyncpg
Home-page: https://github.com/python-trio/triopg
Author: Emmanuel Leblond
Author-email: emmanuel.leblond@gmail.com
License: MIT -or- Apache License 2.0
Keywords: async,trio,sql,postgresql,asyncpg
Platform: UNKNOWN
Classifier: License :: OSI Approved :: MIT License
Classifier: License :: OSI Approved :: Apache Software License
Classifier: Framework :: Trio
Classifier: Operating System :: POSIX :: Linux
Classifier: Operating System :: MacOS :: MacOS X
Classifier: Operating System :: Microsoft :: Windows
Classifier: Programming Language :: Python :: 3 :: Only
Classifier: Programming Language :: Python :: Implementation :: CPython
Classifier: Programming Language :: Python :: Implementation :: PyPy
Classifier: Programming Language :: SQL
Requires-Python: >=3.6
Requires-Dist: asyncpg (>=0.15.0)
Requires-Dist: trio-asyncio (>=0.9.0)
Requires-Dist: trio (>=0.7.0)
